aliyunsdkvcs/__init__.py
aliyunsdkvcs/endpoint.py
aliyunsdkvcs/request/__init__.py
aliyunsdkvcs/request/v20200515/AddDataSourceRequest.py
aliyunsdkvcs/request/v20200515/AddDeviceRequest.py
aliyunsdkvcs/request/v20200515/AddMonitorRequest.py
aliyunsdkvcs/request/v20200515/AddProfileCatalogRequest.py
aliyunsdkvcs/request/v20200515/AddProfileRequest.py
aliyunsdkvcs/request/v20200515/BindCorpGroupRequest.py
aliyunsdkvcs/request/v20200515/BindPersonRequest.py
aliyunsdkvcs/request/v20200515/BindUserRequest.py
aliyunsdkvcs/request/v20200515/CreateCorpGroupRequest.py
aliyunsdkvcs/request/v20200515/CreateCorpRequest.py
aliyunsdkvcs/request/v20200515/CreateUserGroupRequest.py
aliyunsdkvcs/request/v20200515/CreateUserRequest.py
aliyunsdkvcs/request/v20200515/CreateVideoComposeTaskRequest.py
aliyunsdkvcs/request/v20200515/CreateVideoSummaryTaskRequest.py
aliyunsdkvcs/request/v20200515/DeleteCorpGroupRequest.py
aliyunsdkvcs/request/v20200515/DeleteDataSourceRequest.py
aliyunsdkvcs/request/v20200515/DeleteDeviceRequest.py
aliyunsdkvcs/request/v20200515/DeleteProfileCatalogRequest.py
aliyunsdkvcs/request/v20200515/DeleteProfileRequest.py
aliyunsdkvcs/request/v20200515/DeleteRecordsRequest.py
aliyunsdkvcs/request/v20200515/DeleteUserGroupRequest.py
aliyunsdkvcs/request/v20200515/DeleteUserRequest.py
aliyunsdkvcs/request/v20200515/DeleteVideoSummaryTaskRequest.py
aliyunsdkvcs/request/v20200515/DescribeDevicesRequest.py
aliyunsdkvcs/request/v20200515/GetBodyOptionsRequest.py
aliyunsdkvcs/request/v20200515/GetCatalogListRequest.py
aliyunsdkvcs/request/v20200515/GetDeviceConfigRequest.py
aliyunsdkvcs/request/v20200515/GetDeviceLiveUrlRequest.py
aliyunsdkvcs/request/v20200515/GetDeviceVideoUrlRequest.py
aliyunsdkvcs/request/v20200515/GetFaceModelResultRequest.py
aliyunsdkvcs/request/v20200515/GetFaceOptionsRequest.py
aliyunsdkvcs/request/v20200515/GetInventoryRequest.py
aliyunsdkvcs/request/v20200515/GetMonitorListRequest.py
aliyunsdkvcs/request/v20200515/GetMonitorResultRequest.py
aliyun_python_sdk_vcs-2.0.2.dist-info/LICENSE
aliyun_python_sdk_vcs-2.0.2.dist-info/METADATA
aliyun_python_sdk_vcs-2.0.2.dist-info/WHEEL
aliyun_python_sdk_vcs-2.0.2.dist-info/top_level.txt
aliyun_python_sdk_vcs-2.0.2.dist-info/RECORD
